prompted_art_api/__init__.py
prompted_art_api/client.py
prompted_art_api-0.0.1.dist-info/METADATA
prompted_art_api-0.0.1.dist-info/WHEEL
prompted_art_api-0.0.1.dist-info/licenses/LICENSE
prompted_art_api-0.0.1.dist-info/RECORD
