Metadata-Version: 2.1
Name: prompted-art-api
Version: 0.0.1
Summary: An API REST client for Prompted.art
Project-URL: Homepage, https://github.com/mpuig/prompted-art-api-client
Author-email: Marc Puig <marc.puig@gmail.com>
License: MIT License
License-File: LICENSE
Keywords: API,REST,generative art,stable diffusion
Classifier: Intended Audience :: Developers
Classifier: License :: OSI Approved :: MIT License
Classifier: Operating System :: OS Independent
Classifier: Programming Language :: Python :: 3
Classifier: Topic :: Artistic Software
Requires-Python: >=3.7
